primitivegallery/templatetags
primitivegallery
