Metadata-Version: 1.1
Name: django-primitivegallery
Version: 0.0.3
Summary: A simple image gallery.
Home-page: https://github.com/ludw/django-primitivegallery
Author: Ludvig Wadenstein
Author-email: ludvigw@gmail.com
License: MIT
Keywords: django,gallery,images
Platform: UNKNOWN
Classifier: Development Status :: 3 - Alpha
Classifier: Environment :: Web Environment
Classifier: Framework :: Django
Classifier: License :: OSI Approved :: BSD License
Classifier: Operating System :: OS Independent
Classifier: Programming Language :: JavaScript
Classifier: Programming Language :: Python :: 2.7
Classifier: Topic :: Internet :: WWW/HTTP
Classifier: Topic :: Internet :: WWW/HTTP :: Dynamic Content
Classifier: Topic :: Software Development :: Libraries :: Python Modules
